{
    "action_info": {
        "elem_class": "div", 
        "elem_info": {
            "behavior": "", 
            "checkable": false, 
            "class": "div", 
            "clickable": false, 
            "content-desc": "", 
            "enabled": false, 
            "focusable": false, 
            "focused": false, 
            "hash": "j+XGHmQroxcJ16tRXSzBcQ==\n", 
            "height": 31, 
            "hier_level": 0, 
            "human_hash": "div_X53_Y19_W81_H31", 
            "index": -1, 
            "internal": {
                "elem_dict": {
                    "attributes": {
                        "class": "css-0"
                    }, 
                    "background-color": "rgba(0, 0, 0, 0)", 
                    "class": "div", 
                    "color": "rgb(255, 255, 255)", 
                    "cssClass": "css-0", 
                    "domLevel": 8, 
                    "flags": {
                        "checkable": false, 
                        "clickable": false, 
                        "enabled": false, 
                        "focusable": false, 
                        "focused": false, 
                        "scrollable": false
                    }, 
                    "font-family": "\"IBM Plex Sans\", sans-serif", 
                    "font-weight": "700", 
                    "fontSize": 16, 
                    "height": 31, 
                    "identifier": "", 
                    "is-focused": false, 
                    "is-hidden": false, 
                    "name": "", 
                    "tagName": "div", 
                    "text": "Select App", 
                    "type": "", 
                    "value": "", 
                    "width": 81, 
                    "x": 53, 
                    "xPercent": 2.7604166666666665, 
                    "y": 19, 
                    "yPercent": 1.9331243469174502
                }, 
                "location": {
                    "x": 53, 
                    "y": 19
                }, 
                "size": {
                    "height": 31, 
                    "width": 81
                }, 
                "tag_name": "div", 
                "text": "Select App"
            }, 
            "is_transformed": true, 
            "package": "", 
            "password": false, 
            "resource-id": "", 
            "scrollable": false, 
            "tag_name": "div", 
            "text": "Select App", 
            "transformed": true, 
            "width": 81, 
            "x": 53, 
            "y": 19
        }, 
        "gesture": "tap", 
        "text": "tap"
    }, 
    "all_elems": [
        {
            "behavior": "", 
            "checkable": false, 
            "class": "div", 
            "clickable": false, 
            "content-desc": "", 
            "enabled": false, 
            "focusable": false, 
            "focused": false, 
            "hash": "vXr6a3BtNhJ2fahGbVB2tw==\n", 
            "height": 59, 
            "hier_level": 0, 
            "human_hash": "div_X260_Y148_W1400_H59", 
            "index": -1, 
            "internal": {
                "elem_dict": {
                    "attributes": {
                        "class": "container"
                    }, 
                    "background-color": "rgb(255, 255, 255)", 
                    "class": "div", 
                    "color": "rgb(26, 32, 44)", 
                    "cssClass": "container", 
                    "domLevel": 3, 
                    "flags": {
                        "checkable": false, 
                        "clickable": false, 
                        "enabled": false, 
                        "focusable": false, 
                        "focused": false, 
                        "scrollable": false
                    }, 
                    "font-family": "\"IBM Plex Sans\", sans-serif", 
                    "font-weight": "400", 
                    "fontSize": 13, 
                    "height": 59, 
                    "identifier": "", 
                    "is-focused": false, 
                    "is-hidden": false, 
                    "name": "", 
                    "tagName": "div", 
                    "text": "Please select an app on the top left.", 
                    "type": "", 
                    "value": "", 
                    "width": 1400, 
                    "x": 260, 
                    "xPercent": 13.541666666666666, 
                    "y": 148, 
                    "yPercent": 15.464994775339601
                }, 
                "location": {
                    "x": 260, 
                    "y": 148
                }, 
                "size": {
                    "height": 59, 
                    "width": 1400
                }, 
                "tag_name": "div", 
                "text": "Please select an app on the top left."
            }, 
            "is_transformed": true, 
            "package": "", 
            "password": false, 
            "resource-id": "", 
            "scrollable": false, 
            "tag_name": "div", 
            "text": "Please select an app on the top left.", 
            "transformed": true, 
            "width": 1400, 
            "x": 260, 
            "y": 148
        }, 
        {
            "behavior": "", 
            "checkable": false, 
            "class": "div", 
            "clickable": false, 
            "content-desc": "", 
            "enabled": false, 
            "focusable": false, 
            "focused": false, 
            "hash": "rsqIt1cBYijQhtfqmrJzsQ==\n", 
            "height": 37, 
            "hier_level": 0, 
            "human_hash": "div_X1753_Y920_W140_H37", 
            "index": -1, 
            "internal": {
                "elem_dict": {
                    "attributes": {
                        "class": "loadingWave"
                    }, 
                    "background-color": "rgba(0, 0, 0, 0)", 
                    "class": "div", 
                    "color": "rgb(255, 255, 255)", 
                    "cssClass": "loadingWave", 
                    "domLevel": 3, 
                    "flags": {
                        "checkable": false, 
                        "clickable": false, 
                        "enabled": false, 
                        "focusable": false, 
                        "focused": false, 
                        "scrollable": false
                    }, 
                    "font-family": "Inter", 
                    "font-weight": "500", 
                    "fontSize": 18, 
                    "height": 37, 
                    "identifier": "", 
                    "is-focused": false, 
                    "is-hidden": false, 
                    "name": "", 
                    "tagName": "div", 
                    "text": "", 
                    "type": "", 
                    "value": "", 
                    "width": 140, 
                    "x": 1753, 
                    "xPercent": 91.30208333333333, 
                    "y": 920, 
                    "yPercent": 96.1337513061651
                }, 
                "location": {
                    "x": 1753, 
                    "y": 920
                }, 
                "size": {
                    "height": 37, 
                    "width": 140
                }, 
                "tag_name": "div", 
                "text": ""
            }, 
            "is_transformed": true, 
            "package": "", 
            "password": false, 
            "resource-id": "", 
            "scrollable": false, 
            "tag_name": "div", 
            "text": "", 
            "transformed": true, 
            "width": 140, 
            "x": 1753, 
            "y": 920
        }, 
        {
            "behavior": "", 
            "checkable": false, 
            "class": "img", 
            "clickable": false, 
            "content-desc": "", 
            "enabled": false, 
            "focusable": false, 
            "focused": false, 
            "hash": "THV6xBbr3/X3DVbPuWZ9+w==\n", 
            "height": 30, 
            "hier_level": 0, 
            "human_hash": "img_X1839_Y17_W31_H30", 
            "index": -1, 
            "internal": {
                "elem_dict": {
                    "attributes": {
                        "class": "chakra-image css-843btt", 
                        "src": "/images/vapor/icon-profile.svg"
                    }, 
                    "background-color": "rgba(0, 0, 0, 0)", 
                    "class": "img", 
                    "color": "rgb(247, 250, 252)", 
                    "cssClass": "chakra-image css-843btt", 
                    "domLevel": 5, 
                    "flags": {
                        "checkable": false, 
                        "clickable": false, 
                        "enabled": false, 
                        "focusable": false, 
                        "focused": false, 
                        "scrollable": false
                    }, 
                    "font-family": "\"IBM Plex Sans\", sans-serif", 
                    "font-weight": "700", 
                    "fontSize": 16, 
                    "height": 30, 
                    "identifier": "", 
                    "is-focused": false, 
                    "is-hidden": false, 
                    "name": "", 
                    "tagName": "img", 
                    "text": "", 
                    "type": "", 
                    "value": "", 
                    "width": 31, 
                    "x": 1839, 
                    "xPercent": 95.78450520833334, 
                    "y": 17, 
                    "yPercent": 1.7763845350052248
                }, 
                "location": {
                    "x": 1839, 
                    "y": 17
                }, 
                "size": {
                    "height": 30, 
                    "width": 31
                }, 
                "tag_name": "img", 
                "text": ""
            }, 
            "is_transformed": true, 
            "package": "", 
            "password": false, 
            "resource-id": "", 
            "scrollable": false, 
            "tag_name": "img", 
            "text": "", 
            "transformed": true, 
            "width": 31, 
            "x": 1839, 
            "y": 17
        }, 
        {
            "behavior": "", 
            "checkable": false, 
            "class": "div", 
            "clickable": false, 
            "content-desc": "", 
            "enabled": false, 
            "focusable": false, 
            "focused": false, 
            "hash": "f+DVocLq72jiqRuqtM5l5g==\n", 
            "height": 16, 
            "hier_level": 0, 
            "human_hash": "div_X33_Y26_W20_H16", 
            "index": -1, 
            "internal": {
                "elem_dict": {
                    "attributes": {
                        "class": "fas fa-angle-down css-1p2jtab"
                    }, 
                    "background-color": "rgba(0, 0, 0, 0)", 
                    "class": "div", 
                    "color": "rgb(255, 255, 255)", 
                    "cssClass": "fas fa-angle-down css-1p2jtab", 
                    "domLevel": 8, 
                    "flags": {
                        "checkable": false, 
                        "clickable": false, 
                        "enabled": false, 
                        "focusable": false, 
                        "focused": false, 
                        "scrollable": false
                    }, 
                    "font-family": "\"Font Awesome 5 Free\"", 
                    "font-weight": "900", 
                    "fontSize": 16, 
                    "height": 16, 
                    "identifier": "", 
                    "is-focused": false, 
                    "is-hidden": false, 
                    "name": "", 
                    "tagName": "div", 
                    "text": "", 
                    "type": "", 
                    "value": "", 
                    "width": 20, 
                    "x": 33, 
                    "xPercent": 1.7187500000000002, 
                    "y": 26, 
                    "yPercent": 2.7168234064785786
                }, 
                "location": {
                    "x": 33, 
                    "y": 26
                }, 
                "size": {
                    "height": 16, 
                    "width": 20
                }, 
                "tag_name": "div", 
                "text": ""
            }, 
            "is_transformed": true, 
            "package": "", 
            "password": false, 
            "resource-id": "", 
            "scrollable": false, 
            "tag_name": "div", 
            "text": "", 
            "transformed": true, 
            "width": 20, 
            "x": 33, 
            "y": 26
        }, 
        {
            "behavior": "", 
            "checkable": false, 
            "class": "div", 
            "clickable": false, 
            "content-desc": "", 
            "enabled": false, 
            "focusable": false, 
            "focused": false, 
            "hash": "ScW13AMIX5lOqJdVB/7VdQ==\n", 
            "height": 31, 
            "hier_level": 0, 
            "human_hash": "div_X33_Y17_W328_H31", 
            "index": -1, 
            "internal": {
                "elem_dict": {
                    "attributes": {
                        "class": "select active", 
                        "id": ""
                    }, 
                    "background-color": "rgba(0, 0, 0, 0)", 
                    "class": "div", 
                    "color": "rgb(247, 250, 252)", 
                    "cssClass": "select active", 
                    "domLevel": 6, 
                    "flags": {
                        "checkable": false, 
                        "clickable": false, 
                        "enabled": false, 
                        "focusable": false, 
                        "focused": false, 
                        "scrollable": false
                    }, 
                    "font-family": "\"IBM Plex Sans\", sans-serif", 
                    "font-weight": "700", 
                    "fontSize": 16, 
                    "height": 31, 
                    "identifier": "", 
                    "is-focused": false, 
                    "is-hidden": false, 
                    "name": "", 
                    "tagName": "div", 
                    "text": "Select AppAdd an appEquinoxTestAI UI Platform", 
                    "type": "", 
                    "value": "", 
                    "width": 328, 
                    "x": 33, 
                    "xPercent": 1.7187500000000002, 
                    "y": 17, 
                    "yPercent": 1.7241379310344827
                }, 
                "location": {
                    "x": 33, 
                    "y": 17
                }, 
                "size": {
                    "height": 31, 
                    "width": 328
                }, 
                "tag_name": "div", 
                "text": "Select AppAdd an appEquinoxTestAI UI Platform"
            }, 
            "is_transformed": true, 
            "package": "", 
            "password": false, 
            "resource-id": "", 
            "scrollable": false, 
            "tag_name": "div", 
            "text": "Select AppAdd an appEquinoxTestAI UI Platform", 
            "transformed": true, 
            "width": 328, 
            "x": 33, 
            "y": 17
        }, 
        {
            "behavior": "", 
            "checkable": false, 
            "class": "div", 
            "clickable": false, 
            "content-desc": "", 
            "enabled": false, 
            "focusable": false, 
            "focused": false, 
            "hash": "j+XGHmQroxcJ16tRXSzBcQ==\n", 
            "height": 31, 
            "hier_level": 0, 
            "human_hash": "div_X53_Y19_W81_H31", 
            "index": -1, 
            "internal": {
                "elem_dict": {
                    "attributes": {
                        "class": "css-0"
                    }, 
                    "background-color": "rgba(0, 0, 0, 0)", 
                    "class": "div", 
                    "color": "rgb(255, 255, 255)", 
                    "cssClass": "css-0", 
                    "domLevel": 8, 
                    "flags": {
                        "checkable": false, 
                        "clickable": false, 
                        "enabled": false, 
                        "focusable": false, 
                        "focused": false, 
                        "scrollable": false
                    }, 
                    "font-family": "\"IBM Plex Sans\", sans-serif", 
                    "font-weight": "700", 
                    "fontSize": 16, 
                    "height": 31, 
                    "identifier": "", 
                    "is-focused": false, 
                    "is-hidden": false, 
                    "name": "", 
                    "tagName": "div", 
                    "text": "Select App", 
                    "type": "", 
                    "value": "", 
                    "width": 81, 
                    "x": 53, 
                    "xPercent": 2.7604166666666665, 
                    "y": 19, 
                    "yPercent": 1.9331243469174502
                }, 
                "location": {
                    "x": 53, 
                    "y": 19
                }, 
                "size": {
                    "height": 31, 
                    "width": 81
                }, 
                "tag_name": "div", 
                "text": "Select App"
            }, 
            "is_transformed": true, 
            "package": "", 
            "password": false, 
            "resource-id": "", 
            "scrollable": false, 
            "tag_name": "div", 
            "text": "Select App", 
            "transformed": true, 
            "width": 81, 
            "x": 53, 
            "y": 19
        }, 
        {
            "behavior": "", 
            "checkable": false, 
            "class": "div", 
            "clickable": false, 
            "content-desc": "", 
            "enabled": false, 
            "focusable": false, 
            "focused": false, 
            "hash": "KSVSeT+VZJabHYgxXe5fMA==\n", 
            "height": 42, 
            "hier_level": 0, 
            "human_hash": "div_X1719_Y22_W80_H42", 
            "index": -1, 
            "internal": {
                "elem_dict": {
                    "attributes": {
                        "class": "nav css-10mgjfk"
                    }, 
                    "background-color": "rgba(0, 0, 0, 0)", 
                    "class": "div", 
                    "color": "rgb(247, 250, 252)", 
                    "cssClass": "nav css-10mgjfk", 
                    "domLevel": 5, 
                    "flags": {
                        "checkable": false, 
                        "clickable": false, 
                        "enabled": false, 
                        "focusable": false, 
                        "focused": false, 
                        "scrollable": false
                    }, 
                    "font-family": "\"IBM Plex Sans\", sans-serif", 
                    "font-weight": "700", 
                    "fontSize": 16, 
                    "height": 42, 
                    "identifier": "", 
                    "is-focused": false, 
                    "is-hidden": false, 
                    "name": "", 
                    "tagName": "div", 
                    "text": "", 
                    "type": "", 
                    "value": "", 
                    "width": 80, 
                    "x": 1719, 
                    "xPercent": 89.53450520833334, 
                    "y": 22, 
                    "yPercent": 2.3413009404388716
                }, 
                "location": {
                    "x": 1719, 
                    "y": 22
                }, 
                "size": {
                    "height": 42, 
                    "width": 80
                }, 
                "tag_name": "div", 
                "text": ""
            }, 
            "is_transformed": true, 
            "package": "", 
            "password": false, 
            "resource-id": "", 
            "scrollable": false, 
            "tag_name": "div", 
            "text": "", 
            "transformed": true, 
            "width": 80, 
            "x": 1719, 
            "y": 22
        }, 
        {
            "behavior": "", 
            "checkable": false, 
            "class": "div", 
            "clickable": false, 
            "content-desc": "", 
            "enabled": false, 
            "focusable": false, 
            "focused": false, 
            "hash": "9gAElriKIPMx8vLDZpv3hQ==\n", 
            "height": 64, 
            "hier_level": 0, 
            "human_hash": "div_X1719_Y0_W151_H64", 
            "index": -1, 
            "internal": {
                "elem_dict": {
                    "attributes": {
                        "class": "css-azx95j"
                    }, 
                    "background-color": "rgba(0, 0, 0, 0)", 
                    "class": "div", 
                    "color": "rgb(247, 250, 252)", 
                    "cssClass": "css-azx95j", 
                    "domLevel": 4, 
                    "flags": {
                        "checkable": false, 
                        "clickable": false, 
                        "enabled": false, 
                        "focusable": false, 
                        "focused": false, 
                        "scrollable": false
                    }, 
                    "font-family": "\"IBM Plex Sans\", sans-serif", 
                    "font-weight": "700", 
                    "fontSize": 16, 
                    "height": 64, 
                    "identifier": "", 
                    "is-focused": false, 
                    "is-hidden": false, 
                    "name": "", 
                    "tagName": "div", 
                    "text": "", 
                    "type": "", 
                    "value": "", 
                    "width": 151, 
                    "x": 1719, 
                    "xPercent": 89.53450520833334, 
                    "y": 0, 
                    "yPercent": 0
                }, 
                "location": {
                    "x": 1719, 
                    "y": 0
                }, 
                "size": {
                    "height": 64, 
                    "width": 151
                }, 
                "tag_name": "div", 
                "text": ""
            }, 
            "is_transformed": true, 
            "package": "", 
            "password": false, 
            "resource-id": "", 
            "scrollable": false, 
            "tag_name": "div", 
            "text": "", 
            "transformed": true, 
            "width": 151, 
            "x": 1719, 
            "y": 0
        }, 
        {
            "behavior": "", 
            "checkable": false, 
            "class": "div", 
            "clickable": false, 
            "content-desc": "", 
            "enabled": false, 
            "focusable": false, 
            "focused": false, 
            "hash": "DuBMGfqKyAtT3X66ql69dQ==\n", 
            "height": 64, 
            "hier_level": 0, 
            "human_hash": "div_X0_Y0_W1920_H64", 
            "index": -1, 
            "internal": {
                "elem_dict": {
                    "attributes": {
                        "class": "css-11mduyw"
                    }, 
                    "background-color": "rgb(20, 17, 96)", 
                    "class": "div", 
                    "color": "rgb(247, 250, 252)", 
                    "cssClass": "css-11mduyw", 
                    "domLevel": 3, 
                    "flags": {
                        "checkable": false, 
                        "clickable": false, 
                        "enabled": false, 
                        "focusable": false, 
                        "focused": false, 
                        "scrollable": false
                    }, 
                    "font-family": "\"IBM Plex Sans\", sans-serif", 
                    "font-weight": "700", 
                    "fontSize": 16, 
                    "height": 64, 
                    "identifier": "", 
                    "is-focused": false, 
                    "is-hidden": false, 
                    "name": "", 
                    "tagName": "div", 
                    "text": "Select AppAdd an appEquinoxTestAI UI Platform", 
                    "type": "", 
                    "value": "", 
                    "width": 1920, 
                    "x": 0, 
                    "xPercent": 0, 
                    "y": 0, 
                    "yPercent": 0
                }, 
                "location": {
                    "x": 0, 
                    "y": 0
                }, 
                "size": {
                    "height": 64, 
                    "width": 1920
                }, 
                "tag_name": "div", 
                "text": "Select AppAdd an appEquinoxTestAI UI Platform"
            }, 
            "is_transformed": true, 
            "package": "", 
            "password": false, 
            "resource-id": "", 
            "scrollable": false, 
            "tag_name": "div", 
            "text": "Select AppAdd an appEquinoxTestAI UI Platform", 
            "transformed": true, 
            "width": 1920, 
            "x": 0, 
            "y": 0
        }, 
        {
            "behavior": "", 
            "checkable": false, 
            "class": "button", 
            "clickable": true, 
            "content-desc": "", 
            "enabled": true, 
            "focusable": true, 
            "focused": false, 
            "hash": "atJQzlNkqV6rGupyUWI06A==\n", 
            "height": 38, 
            "hier_level": 0, 
            "human_hash": "button_X1752_Y919_W142_H38", 
            "index": -1, 
            "internal": {
                "elem_dict": {
                    "attributes": {
                        "class": "container", 
                        "style": "background: rgb(243, 86, 91); border-top: 1px solid rgba(33, 43, 55, 0.3); border-right: 1px solid rgba(33, 43, 55, 0.3); border-bottom: none; border-left: 1px solid rgba(33, 43, 55, 0.3); color: rgb(255, 255, 255); border-image: initial; border-top-left-radius: 3px; border-top-right-radius: 3px; font-weight: 500; box-sizing: border-box;"
                    }, 
                    "background-color": "rgb(243, 86, 91)", 
                    "class": "button", 
                    "color": "rgb(255, 255, 255)", 
                    "cssClass": "container", 
                    "domLevel": 2, 
                    "flags": {
                        "checkable": false, 
                        "clickable": true, 
                        "enabled": true, 
                        "focusable": true, 
                        "focused": false, 
                        "scrollable": false
                    }, 
                    "font-family": "Inter", 
                    "font-weight": "500", 
                    "fontSize": 18, 
                    "height": 38, 
                    "identifier": "", 
                    "is-focused": false, 
                    "is-hidden": false, 
                    "name": "", 
                    "tagName": "button", 
                    "text": "Report Issue", 
                    "type": "", 
                    "value": "", 
                    "width": 142, 
                    "x": 1752, 
                    "xPercent": 91.25, 
                    "y": 919, 
                    "yPercent": 96.02925809822361
                }, 
                "location": {
                    "x": 1752, 
                    "y": 919
                }, 
                "size": {
                    "height": 38, 
                    "width": 142
                }, 
                "tag_name": "button", 
                "text": "Report Issue"
            }, 
            "is_transformed": true, 
            "package": "", 
            "password": false, 
            "resource-id": "", 
            "scrollable": false, 
            "tag_name": "button", 
            "text": "Report Issue", 
            "transformed": true, 
            "width": 142, 
            "x": 1752, 
            "y": 919
        }, 
        {
            "behavior": "", 
            "checkable": false, 
            "class": "div", 
            "clickable": false, 
            "content-desc": "", 
            "enabled": false, 
            "focusable": false, 
            "focused": false, 
            "hash": "LYUs7d5INTy68i0k/i1m5g==\n", 
            "height": 37, 
            "hier_level": 0, 
            "human_hash": "div_X1769_Y920_W108_H37", 
            "index": -1, 
            "internal": {
                "elem_dict": {
                    "attributes": {
                        "class": "contentWrapper"
                    }, 
                    "background-color": "rgba(0, 0, 0, 0)", 
                    "class": "div", 
                    "color": "rgb(255, 255, 255)", 
                    "cssClass": "contentWrapper", 
                    "domLevel": 3, 
                    "flags": {
                        "checkable": false, 
                        "clickable": false, 
                        "enabled": false, 
                        "focusable": false, 
                        "focused": false, 
                        "scrollable": false
                    }, 
                    "font-family": "Inter", 
                    "font-weight": "500", 
                    "fontSize": 18, 
                    "height": 37, 
                    "identifier": "", 
                    "is-focused": false, 
                    "is-hidden": false, 
                    "name": "", 
                    "tagName": "div", 
                    "text": "Report Issue", 
                    "type": "", 
                    "value": "", 
                    "width": 108, 
                    "x": 1769, 
                    "xPercent": 92.13541666666667, 
                    "y": 920, 
                    "yPercent": 96.1337513061651
                }, 
                "location": {
                    "x": 1769, 
                    "y": 920
                }, 
                "size": {
                    "height": 37, 
                    "width": 108
                }, 
                "tag_name": "div", 
                "text": "Report Issue"
            }, 
            "is_transformed": true, 
            "package": "", 
            "password": false, 
            "resource-id": "", 
            "scrollable": false, 
            "tag_name": "div", 
            "text": "Report Issue", 
            "transformed": true, 
            "width": 108, 
            "x": 1769, 
            "y": 920
        }, 
        {
            "behavior": "", 
            "checkable": false, 
            "class": "div", 
            "clickable": false, 
            "content-desc": "", 
            "enabled": false, 
            "focusable": false, 
            "focused": false, 
            "hash": "K4shNSSaKOqbGdHApmGtyw==\n", 
            "height": 31, 
            "hier_level": 0, 
            "human_hash": "div_X30_Y17_W331_H31", 
            "index": -1, 
            "internal": {
                "elem_dict": {
                    "attributes": {}, 
                    "background-color": "rgba(0, 0, 0, 0)", 
                    "class": "div", 
                    "color": "rgb(247, 250, 252)", 
                    "domLevel": 4, 
                    "flags": {
                        "checkable": false, 
                        "clickable": false, 
                        "enabled": false, 
                        "focusable": false, 
                        "focused": false, 
                        "scrollable": false
                    }, 
                    "font-family": "\"IBM Plex Sans\", sans-serif", 
                    "font-weight": "700", 
                    "fontSize": 16, 
                    "height": 31, 
                    "identifier": "", 
                    "is-focused": false, 
                    "is-hidden": false, 
                    "name": "", 
                    "tagName": "div", 
                    "text": "Select AppAdd an appEquinoxTestAI UI Platform", 
                    "type": "", 
                    "value": "", 
                    "width": 331, 
                    "x": 30, 
                    "xPercent": 1.5625, 
                    "y": 17, 
                    "yPercent": 1.7241379310344827
                }, 
                "location": {
                    "x": 30, 
                    "y": 17
                }, 
                "size": {
                    "height": 31, 
                    "width": 331
                }, 
                "tag_name": "div", 
                "text": "Select AppAdd an appEquinoxTestAI UI Platform"
            }, 
            "is_transformed": true, 
            "package": "", 
            "password": false, 
            "resource-id": "", 
            "scrollable": false, 
            "tag_name": "div", 
            "text": "Select AppAdd an appEquinoxTestAI UI Platform", 
            "transformed": true, 
            "width": 331, 
            "x": 30, 
            "y": 17
        }, 
        {
            "behavior": "", 
            "checkable": false, 
            "class": "div", 
            "clickable": false, 
            "content-desc": "", 
            "enabled": false, 
            "focusable": false, 
            "focused": false, 
            "hash": "jjdgvUG31eopYd0sUKLXoA==\n", 
            "height": 35, 
            "hier_level": 0, 
            "human_hash": "div_X33_Y17_W328_H35", 
            "index": -1, 
            "internal": {
                "elem_dict": {
                    "attributes": {
                        "class": "option default css-lvbb2h", 
                        "id": "name_id"
                    }, 
                    "background-color": "rgba(0, 0, 0, 0)", 
                    "class": "div", 
                    "color": "rgb(255, 255, 255)", 
                    "cssClass": "option default css-lvbb2h", 
                    "domLevel": 7, 
                    "flags": {
                        "checkable": false, 
                        "clickable": false, 
                        "enabled": false, 
                        "focusable": false, 
                        "focused": false, 
                        "scrollable": false
                    }, 
                    "font-family": "\"IBM Plex Sans\", sans-serif", 
                    "font-weight": "700", 
                    "fontSize": 16, 
                    "height": 35, 
                    "identifier": "name_id", 
                    "is-focused": false, 
                    "is-hidden": false, 
                    "name": "", 
                    "tagName": "div", 
                    "text": "Select App", 
                    "type": "", 
                    "value": "", 
                    "width": 328, 
                    "x": 33, 
                    "xPercent": 1.7187500000000002, 
                    "y": 17, 
                    "yPercent": 1.7241379310344827
                }, 
                "location": {
                    "x": 33, 
                    "y": 17
                }, 
                "size": {
                    "height": 35, 
                    "width": 328
                }, 
                "tag_name": "div", 
                "text": "Select App"
            }, 
            "is_transformed": true, 
            "package": "", 
            "password": false, 
            "resource-id": "", 
            "scrollable": false, 
            "tag_name": "div", 
            "text": "Select App", 
            "transformed": true, 
            "width": 328, 
            "x": 33, 
            "y": 17
        }
    ], 
    "cpu": 0, 
    "jank": 0, 
    "mem": 0, 
    "net": 0, 
    "processed": true, 
    "timing": 0
}