{
    "behavior": "", 
    "checkable": false, 
    "class": "a", 
    "clickable": true, 
    "content-desc": "", 
    "enabled": false, 
    "focusable": true, 
    "focused": false, 
    "hash": "Pq88Mg0mZdJj8Px56FgmKg==\n", 
    "height": 42, 
    "hier_level": 0, 
    "human_hash": "a_X1505_Y22_W91_H42", 
    "human_readable": "a_1505_22_91_42_a_00000000c304ffaffbfffbfffbff0000000000000000000000000000ffffffff_9d0e0eed63f4a080612e2ccf7a86214d", 
    "image_path": "NDY0MmFkMzdkMWQ5MWQ2ZmM3OGMxOGEwZTVhZGQ2NzY.png", 
    "index": -1, 
    "internal": {
        "elem_dict": {
            "attributes": {
                "class": "css-1egfvmu", 
                "href": "/c/testai/apps/android/f95ae45d-c7a2-478c-8d65-0d92daa1caa1/test_runs"
            }, 
            "background-color": "rgba(0, 0, 0, 0)", 
            "class": "a", 
            "color": "rgb(255, 255, 255)", 
            "cssClass": "css-1egfvmu", 
            "domLevel": 6, 
            "flags": {
                "checkable": false, 
                "clickable": true, 
                "enabled": false, 
                "focusable": true, 
                "focused": false, 
                "scrollable": false
            }, 
            "font-family": "\"IBM Plex Sans\", sans-serif", 
            "font-weight": "700", 
            "fontSize": 16, 
            "height": 42, 
            "identifier": "", 
            "is-focused": false, 
            "is-hidden": false, 
            "name": "", 
            "tagName": "a", 
            "text": "Test Results", 
            "type": "", 
            "value": "", 
            "width": 91, 
            "x": 1505, 
            "xPercent": 78.37158203125, 
            "y": 22, 
            "yPercent": 1.970646437994723
        }, 
        "location": {
            "x": 1505, 
            "y": 22
        }, 
        "size": {
            "height": 42, 
            "width": 91
        }, 
        "tag_name": "a", 
        "text": "Test Results"
    }, 
    "is_transformed": true, 
    "package": "", 
    "password": false, 
    "resource-id": "", 
    "screen_hash": "c4a59f107b6cae56ee5faf63c2f18a8a", 
    "scrollable": false, 
    "tag_name": "a", 
    "text": "Test Results", 
    "transformed": true, 
    "width": 91, 
    "x": 1505, 
    "y": 22
}